ai_gradio/__init__.py
ai_gradio/providers/__init__.py
ai_gradio/providers/anthropic_gradio.py
ai_gradio/providers/browser_use_gradio.py
ai_gradio/providers/cerebras_gradio.py
ai_gradio/providers/cohere_gradio.py
ai_gradio/providers/crewai_gradio.py
ai_gradio/providers/cua_gradio.py
ai_gradio/providers/deepseek_gradio.py
ai_gradio/providers/fireworks_gradio.py
ai_gradio/providers/gemini_gradio.py
ai_gradio/providers/groq_gradio.py
ai_gradio/providers/huggingface_gradio.py
ai_gradio/providers/hyperbolic_gradio.py
ai_gradio/providers/kokoro_gradio.py
ai_gradio/providers/langchain_gradio.py
ai_gradio/providers/lumaai_gradio.py
ai_gradio/providers/minimax_gradio.py
ai_gradio/providers/mistral_gradio.py
ai_gradio/providers/novita_gradio.py
ai_gradio/providers/nvidia_gradio.py
ai_gradio/providers/ollama_gradio.py
ai_gradio/providers/openai_gradio.py
ai_gradio/providers/openrouter_gradio.py
ai_gradio/providers/perplexity_gradio.py
ai_gradio/providers/qwen_gradio.py
ai_gradio/providers/replicate_gradio.py
ai_gradio/providers/sambanova_gradio.py
ai_gradio/providers/smolagents_gradio.py
ai_gradio/providers/swarms_gradio.py
ai_gradio/providers/together_gradio.py
ai_gradio/providers/transformers_gradio.py
ai_gradio/providers/xai_gradio.py
ai_gradio-0.2.58.dist-info/METADATA
ai_gradio-0.2.58.dist-info/WHEEL
ai_gradio-0.2.58.dist-info/RECORD
