Metadata-Version: 2.4
Name: ai-gradio
Version: 0.2.58
Summary: A Python package for creating Gradio applications with AI models
Project-URL: homepage, https://github.com/AK391/ai-gradio
Project-URL: repository, https://github.com/AK391/ai-gradio
Author-email: AK <ahsen.khaliq@gmail.com>
Classifier: License :: OSI Approved :: MIT License
Classifier: Operating System :: OS Independent
Classifier: Programming Language :: Python :: 3
Requires-Python: >=3.10
Requires-Dist: accelerate>=0.27.0
Requires-Dist: bitsandbytes>=0.41.0
Requires-Dist: gradio-webrtc
Requires-Dist: gradio-webrtc[vad]
Requires-Dist: gradio>=5.9.1
Requires-Dist: librosa
Requires-Dist: modelscope-studio
Requires-Dist: numba==0.60.0
Requires-Dist: numpy
Requires-Dist: opencv-python
Requires-Dist: pillow
Requires-Dist: pydub
Requires-Dist: python-dotenv
Requires-Dist: torch>=2.0.0
Requires-Dist: twilio
Requires-Dist: websockets
Provides-Extra: all
Requires-Dist: anthropic>=1.0.0; extra == 'all'
Requires-Dist: browser-use>=0.1.0; extra == 'all'
Requires-Dist: cohere>=5.0.0; extra == 'all'
Requires-Dist: crewai-tools>=0.0.1; extra == 'all'
Requires-Dist: crewai>=0.1.0; extra == 'all'
Requires-Dist: cua-agent[all]>=0.1.0; extra == 'all'
Requires-Dist: cua-computer>=0.1.0; extra == 'all'
Requires-Dist: google-generativeai; extra == 'all'
Requires-Dist: groq>=0.3.0; extra == 'all'
Requires-Dist: huggingface-hub>=0.20.0; extra == 'all'
Requires-Dist: hyperbolic>=1.58.1; extra == 'all'
Requires-Dist: kokoro-onnx>=0.1.0; extra == 'all'
Requires-Dist: langchain-community>=0.0.10; extra == 'all'
Requires-Dist: langchain-core>=0.1.0; extra == 'all'
Requires-Dist: langchain-openai>=0.0.2; extra == 'all'
Requires-Dist: langchain>=0.1.0; extra == 'all'
Requires-Dist: lumaai>=0.0.3; extra == 'all'
Requires-Dist: openai>=1.58.1; extra == 'all'
Requires-Dist: pydantic<3.0.0,>=2.0.0; extra == 'all'
Requires-Dist: requests>=2.31.0; extra == 'all'
Requires-Dist: sambanova>=0.0.1; extra == 'all'
Requires-Dist: soundfile>=0.12.0; extra == 'all'
Requires-Dist: swarm-models<0.4.0,>=0.3.0; extra == 'all'
Requires-Dist: swarms-memory<0.2.0,>=0.1.2; extra == 'all'
Requires-Dist: swarms<7.0.0,>=6.8.9; extra == 'all'
Requires-Dist: tavily-python>=0.3.0; extra == 'all'
Provides-Extra: anthropic
Requires-Dist: anthropic>=1.0.0; extra == 'anthropic'
Provides-Extra: browser
Requires-Dist: browser-use>=0.1.16; extra == 'browser'
Requires-Dist: playwright>=1.49.1; extra == 'browser'
Provides-Extra: cohere
Requires-Dist: cohere>=5.0.0; extra == 'cohere'
Provides-Extra: crewai
Requires-Dist: crewai-tools>=0.0.1; extra == 'crewai'
Requires-Dist: crewai>=0.1.0; extra == 'crewai'
Requires-Dist: langchain-openai>=0.0.2; extra == 'crewai'
Requires-Dist: langchain>=0.1.0; extra == 'crewai'
Provides-Extra: cua
Requires-Dist: cua-agent[all]>=0.1.0; extra == 'cua'
Requires-Dist: cua-computer>=0.1.0; extra == 'cua'
Provides-Extra: deepseek
Requires-Dist: openai>=1.58.1; extra == 'deepseek'
Provides-Extra: dev
Requires-Dist: black; extra == 'dev'
Requires-Dist: flake8; extra == 'dev'
Requires-Dist: isort; extra == 'dev'
Requires-Dist: pytest; extra == 'dev'
Provides-Extra: fireworks
Requires-Dist: openai>=1.58.1; extra == 'fireworks'
Provides-Extra: gemini
Requires-Dist: google-genai==0.3.0; extra == 'gemini'
Requires-Dist: google-generativeai>=0.8.3; extra == 'gemini'
Provides-Extra: groq
Requires-Dist: openai>=1.58.1; extra == 'groq'
Provides-Extra: huggingface
Requires-Dist: huggingface-hub>=0.29.1; extra == 'huggingface'
Provides-Extra: hyperbolic
Requires-Dist: openai>=1.58.1; extra == 'hyperbolic'
Provides-Extra: jupyter
Requires-Dist: e2b-code-interpreter>=0.5.0; extra == 'jupyter'
Requires-Dist: huggingface-hub>=0.20.0; extra == 'jupyter'
Requires-Dist: nbconvert>=7.16.0; extra == 'jupyter'
Requires-Dist: nbformat>=5.9.0; extra == 'jupyter'
Provides-Extra: kokoro
Requires-Dist: huggingface-hub>=0.27.1; extra == 'kokoro'
Requires-Dist: kokoro-onnx>=0.3.3; extra == 'kokoro'
Requires-Dist: soundfile>=0.13.0; extra == 'kokoro'
Provides-Extra: langchain
Requires-Dist: langchain; extra == 'langchain'
Requires-Dist: langchain-community; extra == 'langchain'
Requires-Dist: langchain-core; extra == 'langchain'
Requires-Dist: langchain-openai; extra == 'langchain'
Requires-Dist: tavily-python; extra == 'langchain'
Provides-Extra: lumaai
Requires-Dist: lumaai>=0.0.3; extra == 'lumaai'
Provides-Extra: minimax
Requires-Dist: requests>=2.31.0; extra == 'minimax'
Provides-Extra: mistral
Requires-Dist: mistralai; extra == 'mistral'
Provides-Extra: novita
Requires-Dist: requests>=2.31.0; extra == 'novita'
Provides-Extra: nvidia
Requires-Dist: openai>=1.58.1; extra == 'nvidia'
Provides-Extra: ollama
Requires-Dist: ollama>=0.4.7; extra == 'ollama'
Provides-Extra: openai
Requires-Dist: openai>=1.58.1; extra == 'openai'
Provides-Extra: openrouter
Requires-Dist: openai>=1.58.1; extra == 'openrouter'
Provides-Extra: perplexity
Requires-Dist: openai>=1.58.1; extra == 'perplexity'
Provides-Extra: qwen
Requires-Dist: openai>=1.58.1; extra == 'qwen'
Provides-Extra: replicate
Requires-Dist: replicate>=1.0.4; extra == 'replicate'
Provides-Extra: sambanova
Requires-Dist: openai>=1.58.1; extra == 'sambanova'
Provides-Extra: smolagents
Requires-Dist: smolagents>=0.1.3; extra == 'smolagents'
Provides-Extra: swarms
Requires-Dist: langchain-community>=0.0.10; extra == 'swarms'
Requires-Dist: langchain>=0.1.0; extra == 'swarms'
Requires-Dist: pydantic<3.0.0,>=2.0.0; extra == 'swarms'
Requires-Dist: swarm-models<0.4.0,>=0.3.0; extra == 'swarms'
Requires-Dist: swarms-memory<0.2.0,>=0.1.2; extra == 'swarms'
Requires-Dist: swarms<7.0.0,>=6.8.9; extra == 'swarms'
Provides-Extra: together
Requires-Dist: openai>=1.58.1; extra == 'together'
Provides-Extra: transformers
Requires-Dist: accelerate>=0.27.0; extra == 'transformers'
Requires-Dist: bitsandbytes>=0.41.0; extra == 'transformers'
Requires-Dist: einops>=0.8.0; extra == 'transformers'
Requires-Dist: pillow>=10.4.0; extra == 'transformers'
Requires-Dist: pyvips-binary>=8.16.0; extra == 'transformers'
Requires-Dist: pyvips>=2.2.3; extra == 'transformers'
Requires-Dist: torch>=2.0.0; extra == 'transformers'
Requires-Dist: torchvision>=0.18.1; extra == 'transformers'
Requires-Dist: transformers>=4.37.0; extra == 'transformers'
Provides-Extra: xai
Requires-Dist: openai>=1.58.1; extra == 'xai'
